[
  {
    "id": "crm",
    "title": "crm",
    "emoji": "📁",
    "description": "Tables belonging to the crm module",
    "tables": [
      "crm_lead_scoring_frequency",
      "crm_lead_scoring_frequency_field",
      "crm_lead",
      "crm_stage",
      "crm_team",
      "crm_lost_reason",
      "crm_recurring_plan"
    ],
    "tags": []
  },
  {
    "id": "sale",
    "title": "sale",
    "emoji": "📁",
    "description": "Tables belonging to the sale module",
    "tables": [
      "sale_order_line",
      "sale_order"
    ],
    "tags": []
  },
  {
    "id": "product",
    "title": "product",
    "emoji": "📁",
    "description": "Tables belonging to the product module",
    "tables": [
      "product_product",
      "product_template",
      "product_combo",
      "product_attribute_custom_value",
      "product_supplierinfo",
      "product_attribute",
      "product_uom",
      "product_document",
      "product_pricelist_item",
      "product_template_attribute_exclusion",
      "product_template_attribute_line",
      "product_category",
      "product_combo_item",
      "product_template_attribute_value",
      "product_pricelist",
      "product_attribute_value",
      "product_tag"
    ],
    "tags": []
  },
  {
    "id": "account",
    "title": "account",
    "emoji": "📁",
    "description": "Tables belonging to the account module",
    "tables": [
      "account_move",
      "account_partial_reconcile",
      "account_account",
      "account_group",
      "account_lock_exception",
      "account_fiscal_position",
      "account_fiscal_position_account",
      "account_incoterms",
      "account_bank_statement_line",
      "account_cash_rounding",
      "account_journal",
      "account_full_reconcile",
      "res_company",
      "account_move_line",
      "res_partner_bank",
      "account_journal_group",
      "account_account_tag",
      "account_payment_method",
      "account_payment_method_line",
      "account_bank_statement",
      "account_tax_group",
      "account_tax",
      "account_tax_repartition_line",
      "account_payment_term",
      "account_payment_term_line",
      "account_reconcile_model_line",
      "account_reconcile_model",
      "res_country_state",
      "account_report",
      "account_report_line",
      "account_report_expression",
      "account_report_column",
      "account_report_external_value",
      "account_payment"
    ],
    "tags": []
  },
  {
    "id": "purchase",
    "title": "purchase",
    "emoji": "📁",
    "description": "Tables belonging to the purchase module",
    "tables": [
      "purchase_order_line",
      "purchase_order"
    ],
    "tags": []
  },
  {
    "id": "stock",
    "title": "stock",
    "emoji": "📁",
    "description": "Tables belonging to the stock module",
    "tables": [
      "stock_warehouse",
      "stock_quant",
      "stock_location",
      "stock_route",
      "stock_reference",
      "stock_scrap",
      "stock_scrap_reason_tag",
      "stock_move",
      "stock_storage_category",
      "stock_storage_category_capacity",
      "stock_lot",
      "product_removal",
      "stock_putaway_rule",
      "stock_picking_type",
      "stock_picking",
      "stock_warehouse_orderpoint",
      "stock_move_line",
      "stock_package",
      "stock_package_type",
      "stock_package_history",
      "stock_rule"
    ],
    "tags": []
  },
  {
    "id": "hr",
    "title": "hr",
    "emoji": "📁",
    "description": "Tables belonging to the hr module",
    "tables": [
      "hr_employee_category",
      "hr_version",
      "hr_department",
      "hr_employee_public",
      "hr_work_location",
      "hr_payroll_structure_type",
      "hr_employee",
      "hr_job",
      "hr_departure_reason",
      "hr_contract_type"
    ],
    "tags": []
  },
  {
    "id": "mail",
    "title": "mail",
    "emoji": "📁",
    "description": "Tables belonging to the mail module",
    "tables": [
      "mail_message_schedule",
      "mail_tracking_value",
      "mail_template",
      "mail_message",
      "mail_message_translation",
      "mail_message_reaction",
      "mail_canned_response",
      "mail_link_preview",
      "ir_cron",
      "mail_ice_server",
      "mail_push_device",
      "mail_alias_domain",
      "res_users_settings_volumes",
      "mail_scheduled_message",
      "mail_message_link_preview",
      "mail_gateway_allowed",
      "res_role",
      "mail_push",
      "mail_followers",
      "mail_activity_plan_template",
      "mail_activity",
      "mail_notification",
      "mail_activity_plan",
      "fetchmail_server",
      "mail_alias",
      "mail_message_subtype",
      "mail_presence",
      "mail_activity_type",
      "mail_mail",
      "mail_blacklist",
      "discuss_channel_rtc_session",
      "mail_guest",
      "discuss_gif_favorite",
      "discuss_voice_metadata",
      "discuss_call_history",
      "discuss_channel_member",
      "discuss_channel"
    ],
    "tags": []
  },
  {
    "id": "website",
    "title": "website",
    "emoji": "📁",
    "description": "Tables belonging to the website module",
    "tables": [
      "res_partner",
      "website_controller_page",
      "ir_module_module",
      "website_track",
      "website_visitor",
      "theme_ir_asset",
      "theme_ir_ui_view",
      "theme_ir_attachment",
      "theme_website_menu",
      "theme_website_page",
      "website",
      "ir_ui_view",
      "website_menu",
      "website_page_properties_base",
      "website_page_properties",
      "ir_model",
      "website_page",
      "website_configurator_feature",
      "website_snippet_filter",
      "website_route",
      "website_rewrite"
    ],
    "tags": []
  },
  {
    "id": "project",
    "title": "project",
    "emoji": "📁",
    "description": "Tables belonging to the project module",
    "tables": [
      "project_project_stage",
      "project_milestone",
      "project_task",
      "project_tags",
      "project_collaborator",
      "project_update",
      "project_task_type",
      "project_task_recurrence",
      "project_project",
      "project_role"
    ],
    "tags": []
  }
]